venv_modulefile-0.1.19.dist-info/licenses/LICENSE.md
venvmod/VERSION
venvmod/__init__.py
venvmod/modulefile.py
venvmod/tools.py
venvmod/commands/__init__.py
venvmod/commands/append_module.py
venvmod/commands/create_module.py
venvmod/commands/test_imports.py
venvmod/modulefiles_src/modules-5.2.0.tar.gz
venvmod/modulefiles_src/modules-5.3.1.tar.gz
venvmod/modulefiles_src/modules-5.4.0.tar.gz
venvmod/modulefiles_src/modules-5.6.0.tar.gz
venv_modulefile-0.1.19.dist-info/METADATA
venv_modulefile-0.1.19.dist-info/WHEEL
venv_modulefile-0.1.19.dist-info/entry_points.txt
venv_modulefile-0.1.19.dist-info/top_level.txt
venv_modulefile-0.1.19.dist-info/RECORD
