Metadata-Version: 2.4
Name: venv-modulefile
Version: 0.1.19
Summary: Python venv extension using Modulefile
Home-page: https://github.com/code-coupling/venv-modulefile
Author: R. Lenain
Author-email: roland.lenain@cea.fr
Project-URL: Bug Reports, https://github.com/code-coupling/venv-modulefile/issues
Project-URL: Doc, https://venv-modulefile.readthedocs.io/en/latest/index.html
Project-URL: Source, https://github.com/code-coupling/venv-modulefile
Keywords: venv,modulefile
Classifier: Development Status :: 3 - Alpha
Classifier: Intended Audience :: Developers
Classifier: Topic :: Scientific/Engineering :: Physics
Classifier: License :: OSI Approved :: BSD License
Classifier: Programming Language :: Python :: 3.6
Classifier: Programming Language :: Python :: 3.7
Classifier: Programming Language :: Python :: 3.8
Classifier: Programming Language :: Python :: 3.9
Classifier: Programming Language :: Python :: 3.10
Classifier: Programming Language :: Python :: 3.11
Requires-Python: >=3.7, <4
License-File: LICENSE.md
Requires-Dist: packaging
Requires-Dist: requests
Requires-Dist: shellingham
Provides-Extra: docs
Requires-Dist: psutil~=7.0; extra == "docs"
Requires-Dist: Sphinx~=8.0; extra == "docs"
Requires-Dist: sphinx-rtd-theme~=3.0; extra == "docs"
Requires-Dist: myst-parser~=4.0; extra == "docs"
Requires-Dist: numpydoc~=1.0; extra == "docs"
Requires-Dist: sphinxcontrib-programoutput; extra == "docs"
Provides-Extra: test
Requires-Dist: psutil~=7.0; extra == "test"
Requires-Dist: pylint>=2.13.9; extra == "test"
Requires-Dist: pytest>=7.0.1; extra == "test"
Requires-Dist: pytest-cov>=4.0.0; extra == "test"
Requires-Dist: pytest-html>=3.2.0; extra == "test"
Requires-Dist: pytest-sugar>=0.9.6; extra == "test"
Requires-Dist: pytest-xdist>=3.0.2; extra == "test"
Dynamic: author
Dynamic: author-email
Dynamic: classifier
Dynamic: description
Dynamic: description-content-type
Dynamic: home-page
Dynamic: keywords
Dynamic: license-file
Dynamic: project-url
Dynamic: provides-extra
Dynamic: requires-dist
Dynamic: requires-python
Dynamic: summary
